robustify/__init__.py
robustify/noise_corruptions.py
robustify/noise/__init__.py
robustify/noise/continuous.py
robustify/noise/discrete.py
robustify/utils/__init__.py
robustify/utils/_filter.py
robustify/utils/_importances.py
robustify/utils/_plot.py
robustify/utils/_predict.py
robustify/utils/_progress.py
robustify/utils/_sampling.py
robustify/utils/_scorers.py
robustify/utils/_train.py
robustify/utils/_transform.py
tests/__init__.py
tests/test_gaussianNoise.py
tests/test_importances.py
tests/test_poissonNoise.py
tests/test_sampling.py
tests/test_scikt-learn_compatibility.py
tests/test_tensorflow_keras_compatibility.py
tests/test_transform.py
RobustifyToolkit-0.1.1.dist-info/LICENSE
RobustifyToolkit-0.1.1.dist-info/METADATA
RobustifyToolkit-0.1.1.dist-info/WHEEL
RobustifyToolkit-0.1.1.dist-info/top_level.txt
RobustifyToolkit-0.1.1.dist-info/RECORD
