Metadata-Version: 2.1
Name: RobustifyToolkit
Version: 0.1.1
Summary: Robustify:
Author: Isabel Foster
License: MIT
Classifier: Development Status :: 3 - Alpha
Classifier: Intended Audience :: Developers
Classifier: Intended Audience :: Education
Classifier: Intended Audience :: Science/Research
Classifier: Programming Language :: Python :: 3.8
Classifier: Programming Language :: Python :: 3.9
Classifier: Programming Language :: Python :: 3.10
Classifier: Topic :: Software Development :: Libraries :: Python Modules
Classifier: Topic :: Scientific/Engineering :: Artificial Intelligence
License-File: LICENSE
Requires-Dist: numpy
Requires-Dist: scikit-learn
Requires-Dist: matplotlib
Requires-Dist: pandas
Requires-Dist: plotly
Requires-Dist: tqdm
Requires-Dist: chart-studio
Requires-Dist: python-dotenv
Requires-Dist: tensorflow
Requires-Dist: kaleido
Requires-Dist: ipython
Requires-Dist: eli5
Requires-Dist: lime
Requires-Dist: shap
Requires-Dist: torch
